qradar/__init__.py
qradar/async_client.py
qradar/cached_client.py
qradar/client.py
qradar-0.0.3.dist-info/METADATA
qradar-0.0.3.dist-info/WHEEL
qradar-0.0.3.dist-info/top_level.txt
qradar-0.0.3.dist-info/RECORD
