Metadata-Version: 2.1
Name: qradar
Version: 0.0.3
Summary: QRadar client for python with API schema fetching
Home-page: https://github.com/Chmele/qradar-client
Author: Chmele
License: MIT
Keywords: client,scripting,qradar,qradar-api
Classifier: Development Status :: 3 - Alpha
Classifier: Intended Audience :: Developers
Classifier: Topic :: Software Development :: Build Tools
Classifier: Programming Language :: Python :: 3
Classifier: Programming Language :: Python :: 3.10
Classifier: Programming Language :: Python :: 3.11
Classifier: Programming Language :: Python :: 3.12
Classifier: Programming Language :: Python :: 3.13
Requires: setuptools
Provides-Extra: httpx
Requires-Dist: httpx>=0.27; extra == "httpx"
Provides-Extra: requests
Requires-Dist: requests>=2.30; extra == "requests"
